azureml/__init__.py
azureml/opendatasets/__init__.py
azureml/opendatasets/_bing_covid_19_data.py
azureml/opendatasets/_boston_safety.py
azureml/opendatasets/_chicago_safety.py
azureml/opendatasets/_city_safety.py
azureml/opendatasets/_covid_19_open_research.py
azureml/opendatasets/_covid_tracking_project.py
azureml/opendatasets/_diabetes.py
azureml/opendatasets/_ecdc_covid_19_cases.py
azureml/opendatasets/_mnist.py
azureml/opendatasets/_no_parameter_open_dataset_base.py
azureml/opendatasets/_noaa_gfs_weather.py
azureml/opendatasets/_noaa_isd_weather.py
azureml/opendatasets/_nyc_safety.py
azureml/opendatasets/_nyc_taxi_base.py
azureml/opendatasets/_nyc_tlc_fhv.py
azureml/opendatasets/_nyc_tlc_green.py
azureml/opendatasets/_nyc_tlc_yellow.py
azureml/opendatasets/_oj_sales_simulated.py
azureml/opendatasets/_opendataset_factory.py
azureml/opendatasets/_public_holidays.py
azureml/opendatasets/_public_holidays_offline.py
azureml/opendatasets/_sample_dataset_base.py
azureml/opendatasets/_sanfrancisco_safety.py
azureml/opendatasets/_seattle_safety.py
azureml/opendatasets/_us_labor_cpi.py
azureml/opendatasets/_us_labor_ehe_national.py
azureml/opendatasets/_us_labor_ehe_state.py
azureml/opendatasets/_us_labor_laus.py
azureml/opendatasets/_us_labor_lfs.py
azureml/opendatasets/_us_labor_ppi_commodity.py
azureml/opendatasets/_us_labor_ppi_industry.py
azureml/opendatasets/_us_population_county.py
azureml/opendatasets/_us_population_zip.py
azureml/opendatasets/environ.py
azureml/opendatasets/_utils/__init__.py
azureml/opendatasets/_utils/blob_pandas_helper.py
azureml/opendatasets/_utils/public_holidays_utils.py
azureml/opendatasets/_utils/random_utils.py
azureml/opendatasets/_utils/spark_utils.py
azureml/opendatasets/_utils/telemetry_utils.py
azureml/opendatasets/_utils/time_utils.py
azureml/opendatasets/_utils/zipcode_mapping.py
azureml/opendatasets/accessories/__init__.py
azureml/opendatasets/accessories/_loggerfactory.py
azureml_opendatasets-1.60.0.dist-info/licenses/LICENSE.txt
azureml_opendatasets-1.60.0.dist-info/METADATA
azureml_opendatasets-1.60.0.dist-info/WHEEL
azureml_opendatasets-1.60.0.dist-info/top_level.txt
azureml_opendatasets-1.60.0.dist-info/RECORD
