Metadata-Version: 2.4
Name: azureml-opendatasets
Version: 1.60.0
Summary: Provides a set of APIs to consume Azure Open Datasets.
Home-page: https://docs.microsoft.com/en-us/azure/open-datasets/
Author: Microsoft Corp
License: Proprietary https://aka.ms/azureml-preview-sdk-license 
Classifier: Development Status :: 5 - Production/Stable
Classifier: Intended Audience :: Developers
Classifier: Intended Audience :: Science/Research
Classifier: License :: Other/Proprietary License
Classifier: Programming Language :: Python :: 3
Classifier: Programming Language :: Python :: 3.8
Classifier: Programming Language :: Python :: 3.9
Classifier: Programming Language :: Python :: 3.10
Classifier: Programming Language :: Python :: 3.11
Classifier: Topic :: Scientific/Engineering :: Artificial Intelligence
Classifier: Operating System :: Microsoft :: Windows
Classifier: Operating System :: MacOS
Classifier: Operating System :: POSIX :: Linux
Requires-Python: >=3.8,<4.0
License-File: LICENSE.txt
Requires-Dist: azureml-telemetry~=1.60.0
Requires-Dist: azureml-core~=1.60.0
Requires-Dist: azureml-dataset-runtime[fuse,pandas]~=1.60.0
Requires-Dist: numpy<=2.0.0,>=1.16.0
Requires-Dist: pandas<=2.0.0,>=0.21.0
Requires-Dist: scipy<=2.0.0,>=1.0.0
Requires-Dist: pyarrow>=0.16.0
Requires-Dist: pyspark
Dynamic: author
Dynamic: classifier
Dynamic: description
Dynamic: description-content-type
Dynamic: home-page
Dynamic: license
Dynamic: license-file
Dynamic: requires-dist
Dynamic: requires-python
Dynamic: summary
